ndp_utils/__init__.py
ndp_utils/env_utils.py
ndp_utils/gitlab_utils.py
ndp_utils/odoo_utils.py
ndp_utils-1.1.1.dist-info/METADATA
ndp_utils-1.1.1.dist-info/WHEEL
ndp_utils-1.1.1.dist-info/top_level.txt
ndp_utils-1.1.1.dist-info/RECORD
