Metadata-Version: 2.1
Name: ndp-utils
Version: 1.1.1
Summary: Allow to find Odoo addons from Environement Variables
Home-page: https://gitlab.ndp-systemes.fr/python-libs/addons_launcher
Author: NDP Systemes
Author-email: opensource@ndp-systemes.fr
License: GPLv3
Classifier: Programming Language :: Python :: 2.7
Classifier: Programming Language :: Python :: 3.6
Classifier: Programming Language :: Python :: 3.7
Classifier: Programming Language :: Python :: 3.8
Classifier: Programming Language :: Python :: 3.9
Classifier: Programming Language :: Python :: 3.10
Requires-Python: !=3.1.*,!=3.2.*,!=3.3.*,!=3.4.*,!=3.5.*,>=2.7
Requires-Dist: python-gitlab (<4,>=3.4.0)
Requires-Dist: typing (==3.10.0.0) ; python_version <= "3"
